<?xml version="1.0" encoding="UTF-8" ?><tv date="20240821">
<channel id="SkySportF1Germany.de"><display-name>Sky Sport F1 HD</display-name><url>https://sky.de</url></channel>
<channel id="SkySportBundesligaUHD.de"><display-name>Sky Sport Bundesliga UHD</display-name><url>https://sky.de</url></channel>
<programme start="20240820223000 +0000" stop="20240820233000 +0000" channel="SkySportF1Germany.de"><title lang="de">F3: 1. Rennen - GP Großbritannien</title><category lang="de">Motorsport</category><icon src="http://sky.de/static/img/program_guide/14522837_s.jpg"/></programme>
<programme start="20240820233000 +0000" stop="20240821003000 +0000" channel="SkySportF1Germany.de"><title lang="de">F3: 2. Rennen - GP Großbritannien</title><category lang="de">Motorsport</category><icon src="http://sky.de/static/img/program_guide/14522843_s.jpg"/></programme>
<programme start="20240821003000 +0000" stop="20240821013000 +0000" channel="SkySportF1Germany.de"><title lang="de">PMSC: Rennen - GP Großbritannien</title><category lang="de">Motorsport</category><icon src="http://sky.de/static/img/program_guide/14522845_s.jpg"/></programme>
<programme start="20240821013000 +0000" stop="20240821020000 +0000" channel="SkySportF1Germany.de"><title lang="de">Extreme E: Electric Odyssey</title><category lang="de">Motorsport</category><icon src="http://sky.de/static/img/program_guide/14407654_s.jpg"/></programme>
<programme start="20240821020000 +0000" stop="20240821030000 +0000" channel="SkySportF1Germany.de"><title lang="de">Ferrari Challenge Europe: Trofeo Pirelli - 1. Rennen in Jerez</title><category lang="de">Motorsport</category><icon src="http://sky.de/static/img/program_guide/14522732_s.jpg"/></programme>
<programme start="20240821030000 +0000" stop="20240821040000 +0000" channel="SkySportF1Germany.de"><title lang="de">Ferrari Challenge Europe: Trofeo Pirelli - 2. Rennen in Jerez</title><category lang="de">Motorsport</category><icon src="http://sky.de/static/img/program_guide/14522733_s.jpg"/></programme>
<programme start="20240821040000 +0000" stop="20240821053000 +0000" channel="SkySportF1Germany.de"><title lang="de">F1: 1. Freies Training - GP Ungarn</title><category lang="de">Formel 1</category><icon src="http://sky.de/static/img/program_guide/14522973_s.jpg"/></programme>
<programme start="20240821053000 +0000" stop="20240821070000 +0000" channel="SkySportF1Germany.de"><title lang="de">F1: 2. Freies Training - GP Ungarn</title><category lang="de">Formel 1</category><icon src="http://sky.de/static/img/program_guide/14522976_s.jpg"/></programme>
<programme start="20240821070000 +0000" stop="20240821083000 +0000" channel="SkySportF1Germany.de"><title lang="de">F1: 3. Freies Training - GP Ungarn</title><category lang="de">Formel 1</category><icon src="http://sky.de/static/img/program_guide/14522979_s.jpg"/></programme>
<programme start="20240821083000 +0000" stop="20240821100000 +0000" channel="SkySportF1Germany.de"><title lang="de">F1: Qualifying - GP Ungarn</title><category lang="de">Formel 1</category><icon src="http://sky.de/static/img/program_guide/14522981_s.jpg"/></programme>
<programme start="20240821100000 +0000" stop="20240821120000 +0000" channel="SkySportF1Germany.de"><title lang="de">F1: Rennen - GP Ungarn</title><category lang="de">Formel 1</category><icon src="http://sky.de/static/img/program_guide/14522987_s.jpg"/></programme>
<programme start="20240821120000 +0000" stop="20240821140000 +0000" channel="SkySportF1Germany.de"><title lang="de">IndyCar: Bommarito Automotive Group 500</title><category lang="de">Motorsport</category><icon src="http://sky.de/static/img/program_guide/14457541_s.jpg"/></programme>
<programme start="20240821140000 +0000" stop="20240821150000 +0000" channel="SkySportF1Germany.de"><title lang="de">PMSC: Rennen - GP Ungarn</title><category lang="de">Motorsport</category><icon src="http://sky.de/static/img/program_guide/14522985_s.jpg"/></programme>
<programme start="20240821150000 +0000" stop="20240821160000 +0000" channel="SkySportF1Germany.de"><title lang="de">F2: 1. Rennen - GP Ungarn</title><category lang="de">Motorsport</category><icon src="http://sky.de/static/img/program_guide/14522980_s.jpg"/></programme>
<programme start="20240821160000 +0000" stop="20240821170000 +0000" channel="SkySportF1Germany.de"><title lang="de">F2: 2. Rennen - GP Ungarn</title><category lang="de">Motorsport</category><icon src="http://sky.de/static/img/program_guide/14522984_s.jpg"/></programme>
<programme start="20240821170000 +0000" stop="20240821171500 +0000" channel="SkySportF1Germany.de"><title lang="de">F1: Top 10 Onboards: GP Belgien</title><category lang="de">Formel 1</category><icon src="http://sky.de/static/img/program_guide/14523033_s.jpg"/></programme>
<programme start="20240821171500 +0000" stop="20240821191500 +0000" channel="SkySportF1Germany.de"><title lang="de">F1: Rennen - GP Ungarn</title><category lang="de">Formel 1</category><icon src="http://sky.de/static/img/program_guide/14522987_s.jpg"/></programme>
<programme start="20240821191500 +0000" stop="20240821193000 +0000" channel="SkySportF1Germany.de"><title lang="de">F1: Top 10 Onboards: GP Ungarn</title><category lang="de">Formel 1</category><icon src="http://sky.de/static/img/program_guide/14522994_s.jpg"/></programme>
<programme start="20240821193000 +0000" stop="20240821200000 +0000" channel="SkySportF1Germany.de"><title lang="de">F1: Box Box Box: Red Bulls 1st Win</title><category lang="de">Formel 1</category><icon src="http://sky.de/static/img/program_guide/11777683_s.jpg"/></programme>
<programme start="20240821200000 +0000" stop="20240821210000 +0000" channel="SkySportF1Germany.de"><title lang="de">F3: 1. Rennen - GP Ungarn</title><category lang="de">Motorsport</category><icon src="http://sky.de/static/img/program_guide/14522978_s.jpg"/></programme>
<programme start="20240821210000 +0000" stop="20240821220000 +0000" channel="SkySportF1Germany.de"><title lang="de">F3: 2. Rennen - GP Ungarn</title><category lang="de">Motorsport</category><icon src="http://sky.de/static/img/program_guide/14522983_s.jpg"/></programme>
<programme start="20240821220000 +0000" stop="20240821230000 +0000" channel="SkySportF1Germany.de"><title lang="de">PMSC: Rennen - GP Ungarn</title><category lang="de">Motorsport</category><icon src="http://sky.de/static/img/program_guide/14522985_s.jpg"/></programme>
<programme start="20240821230000 +0000" stop="20240822000000 +0000" channel="SkySportF1Germany.de"><title lang="de">F2: 1. Rennen - GP Ungarn</title><category lang="de">Motorsport</category><icon src="http://sky.de/static/img/program_guide/14522980_s.jpg"/></programme>
<programme start="20240822000000 +0000" stop="20240822010000 +0000" channel="SkySportF1Germany.de"><title lang="de">F2: 2. Rennen - GP Ungarn</title><category lang="de">Motorsport</category><icon src="http://sky.de/static/img/program_guide/14522984_s.jpg"/></programme>
<programme start="20240822010000 +0000" stop="20240822020000 +0000" channel="SkySportF1Germany.de"><title lang="de">IndyCar: Highlights: Bommarito Automotive Group 500</title><category lang="de">Motorsport</category></programme>
<programme start="20240822020000 +0000" stop="20240822030000 +0000" channel="SkySportF1Germany.de"><title lang="de">Ferrari Challenge Europe: Trofeo Pirelli - 1. Rennen in Portimão</title><category lang="de">Motorsport</category><icon src="http://sky.de/static/img/program_guide/14522826_s.jpg"/></programme>
<programme start="20240822030000 +0000" stop="20240822040000 +0000" channel="SkySportF1Germany.de"><title lang="de">Ferrari Challenge Europe: Trofeo Pirelli - 2. Rennen in Portimão</title><category lang="de">Motorsport</category><icon src="http://sky.de/static/img/program_guide/14522827_s.jpg"/></programme>
<programme start="20240822040000 +0000" stop="20240822053000 +0000" channel="SkySportF1Germany.de"><title lang="de">F1: 1. Freies Training - GP Belgien</title><category lang="de">Formel 1</category><icon src="http://sky.de/static/img/program_guide/14523005_s.jpg"/></programme>
<programme start="20240822053000 +0000" stop="20240822070000 +0000" channel="SkySportF1Germany.de"><title lang="de">F1: 2. Freies Training - GP Belgien</title><category lang="de">Formel 1</category><icon src="http://sky.de/static/img/program_guide/14523008_s.jpg"/></programme>
<programme start="20240822070000 +0000" stop="20240822083000 +0000" channel="SkySportF1Germany.de"><title lang="de">F1: 3. Freies Training - GP Belgien</title><category lang="de">Formel 1</category><icon src="http://sky.de/static/img/program_guide/14523010_s.jpg"/></programme>
<programme start="20240822083000 +0000" stop="20240822100000 +0000" channel="SkySportF1Germany.de"><title lang="de">F1: Qualifying - GP Belgien</title><category lang="de">Formel 1</category><icon src="http://sky.de/static/img/program_guide/14523011_s.jpg"/></programme>
<programme start="20240822100000 +0000" stop="20240822120000 +0000" channel="SkySportF1Germany.de"><title lang="de">F1: Rennen - GP Belgien</title><category lang="de">Formel 1</category><icon src="http://sky.de/static/img/program_guide/14523027_s.jpg"/></programme>
<programme start="20240822120000 +0000" stop="20240822130000 +0000" channel="SkySportF1Germany.de"><title lang="de">F3: 1. Rennen - GP Belgien</title><category lang="de">Motorsport</category><icon src="http://sky.de/static/img/program_guide/14523014_s.jpg"/></programme>
<programme start="20240822130000 +0000" stop="20240822140000 +0000" channel="SkySportF1Germany.de"><title lang="de">F3: 2. Rennen - GP Belgien</title><category lang="de">Motorsport</category><icon src="http://sky.de/static/img/program_guide/14523023_s.jpg"/></programme>
<programme start="20240822140000 +0000" stop="20240822150000 +0000" channel="SkySportF1Germany.de"><title lang="de">PMSC: Rennen - GP Belgien</title><category lang="de">Motorsport</category><icon src="http://sky.de/static/img/program_guide/14523025_s.jpg"/></programme>
<programme start="20240822150000 +0000" stop="20240822160000 +0000" channel="SkySportF1Germany.de"><title lang="de">F2: 1. Rennen - GP Belgien</title><category lang="de">Motorsport</category><icon src="http://sky.de/static/img/program_guide/14523015_s.jpg"/></programme>
<programme start="20240822160000 +0000" stop="20240822170000 +0000" channel="SkySportF1Germany.de"><title lang="de">F2: 2. Rennen - GP Belgien</title><category lang="de">Motorsport</category><icon src="http://sky.de/static/img/program_guide/14523024_s.jpg"/></programme>
<programme start="20240822170000 +0000" stop="20240822171500 +0000" channel="SkySportF1Germany.de"><title lang="de">F1: Warm Up - Das Motorsport Spezial</title><category lang="de">Formel 1</category><icon src="http://sky.de/static/img/program_guide/14600197_s.jpg"/></programme>
<programme start="20240822171500 +0000" stop="20240822180000 +0000" channel="SkySportF1Germany.de"><title lang="de">F1: Pressekonferenz Fahrer - GP Niederlande</title><category lang="de">Formel 1</category><icon src="http://sky.de/static/img/program_guide/14600234_s.jpg"/></programme>
<programme start="20240822180000 +0000" stop="20240822200000 +0000" channel="SkySportF1Germany.de"><title lang="de">F1: Rennen - GP Belgien</title><category lang="de">Formel 1</category><icon src="http://sky.de/static/img/program_guide/14523027_s.jpg"/></programme>
<programme start="20240822200000 +0000" stop="20240822203000 +0000" channel="SkySportF1Germany.de"><title lang="de">Extreme E: Electric Odyssey</title><category lang="de">Motorsport</category><icon src="http://sky.de/static/img/program_guide/14407655_s.jpg"/></programme>
<programme start="20240822203000 +0000" stop="20240822204500 +0000" channel="SkySportF1Germany.de"><title lang="de">Chasing the Dream: Hadjars Spa Ausbruch</title><category lang="de">Motorsport</category><icon src="http://sky.de/static/img/program_guide/14522997_s.jpg"/></programme>
<programme start="20240822204500 +0000" stop="20240822210000 +0000" channel="SkySportF1Germany.de"><title lang="de">F1: Top 10 Onboards: GP Belgien</title><category lang="de">Formel 1</category><icon src="http://sky.de/static/img/program_guide/14523033_s.jpg"/></programme>
<programme start="20240822210000 +0000" stop="20240822230000 +0000" channel="SkySportF1Germany.de"><title lang="de">IndyCar: Bommarito Automotive Group 500</title><category lang="de">Motorsport</category><icon src="http://sky.de/static/img/program_guide/14457541_s.jpg"/></programme>
<programme start="20240822230000 +0000" stop="20240822233000 +0000" channel="SkySportF1Germany.de"><title lang="de">Extreme E: Electric Odyssey</title><category lang="de">Motorsport</category><icon src="http://sky.de/static/img/program_guide/14407655_s.jpg"/></programme>
<programme start="20240822233000 +0000" stop="20240823000000 +0000" channel="SkySportF1Germany.de"><title lang="de">F1: Box Box Box: Red Bulls 1st Win</title><category lang="de">Formel 1</category><icon src="http://sky.de/static/img/program_guide/11777683_s.jpg"/></programme>
<programme start="20240823000000 +0000" stop="20240823020000 +0000" channel="SkySportF1Germany.de"><title lang="de">F1: Rennen - GP Ungarn</title><category lang="de">Formel 1</category><icon src="http://sky.de/static/img/program_guide/14522987_s.jpg"/></programme>
<programme start="20240823020000 +0000" stop="20240823030000 +0000" channel="SkySportF1Germany.de"><title lang="de">Ferrari Challenge Europe: Trofeo Pirelli - 1. Rennen in Le Castellet</title><category lang="de">Motorsport</category><icon src="http://sky.de/static/img/program_guide/14523019_s.jpg"/></programme>
<programme start="20240823030000 +0000" stop="20240823040000 +0000" channel="SkySportF1Germany.de"><title lang="de">Ferrari Challenge Europe: Trofeo Pirelli - 2. Rennen in Le Castellet</title><category lang="de">Motorsport</category><icon src="http://sky.de/static/img/program_guide/14523021_s.jpg"/></programme>
<programme start="20240823040000 +0000" stop="20240823060000 +0000" channel="SkySportF1Germany.de"><title lang="de">IndyCar: Bommarito Automotive Group 500</title><category lang="de">Motorsport</category><icon src="http://sky.de/static/img/program_guide/14457541_s.jpg"/></programme>
<programme start="20240823060000 +0000" stop="20240823070000 +0000" channel="SkySportF1Germany.de"><title lang="de">F1 Academy: 1. Rennen - GP Spanien</title><category lang="de">Motorsport</category></programme>
<programme start="20240823070000 +0000" stop="20240823080000 +0000" channel="SkySportF1Germany.de"><title lang="de">F1 Academy: 2. Rennen - GP Spanien</title><category lang="de">Motorsport</category></programme>
<programme start="20240823080000 +0000" stop="20240823081000 +0000" channel="SkySportF1Germany.de"><title lang="de">F1: Jessica Hawkins im AMR21</title><category lang="de">Formel 1</category><icon src="http://sky.de/static/img/program_guide/14245891_s.jpg"/></programme>
<programme start="20240823081000 +0000" stop="20240823090000 +0000" channel="SkySportF1Germany.de"><title lang="de">Live F1 Academy: 1. Freies Training - GP Niederlande</title><category lang="de">Motorsport</category><icon src="http://sky.de/static/img/program_guide/14600245_s.jpg"/></programme>
<programme start="20240823090000 +0000" stop="20240823091500 +0000" channel="SkySportF1Germany.de"><title lang="de">Chasing the Dream: Hadjars Spa Ausbruch</title><category lang="de">Motorsport</category><icon src="http://sky.de/static/img/program_guide/14522997_s.jpg"/></programme>
<programme start="20240823091500 +0000" stop="20240823100000 +0000" channel="SkySportF1Germany.de"><title lang="de">F1: Pressekonferenz Fahrer - GP Niederlande</title><category lang="de">Formel 1</category><icon src="http://sky.de/static/img/program_guide/14600234_s.jpg"/></programme>
<programme start="20240823100000 +0000" stop="20240823101500 +0000" channel="SkySportF1Germany.de"><title lang="de">F1: Warm Up - Das Motorsport Spezial</title><category lang="de">Formel 1</category><icon src="http://sky.de/static/img/program_guide/14600197_s.jpg"/></programme>
<programme start="20240823101500 +0000" stop="20240823120000 +0000" channel="SkySportF1Germany.de"><title lang="de">Live F1: 1. Freies Training - GP Niederlande</title><category lang="de">Formel 1</category></programme>
<programme start="20240823120000 +0000" stop="20240823121500 +0000" channel="SkySportF1Germany.de"><title lang="de">F1: Inside Story: Lando wins at last</title><category lang="de">Formel 1</category><icon src="http://sky.de/static/img/program_guide/14667620_s.jpg"/></programme>
<programme start="20240823121500 +0000" stop="20240823123000 +0000" channel="SkySportF1Germany.de"><title lang="de">Chasing the Dream: Hadjars Spa Ausbruch</title><category lang="de">Motorsport</category><icon src="http://sky.de/static/img/program_guide/14522997_s.jpg"/></programme>
<programme start="20240823123000 +0000" stop="20240823133000 +0000" channel="SkySportF1Germany.de"><title lang="de">Live F1: Pressekonferenz Teamchefs - GP Niederlande</title><category lang="de">Formel 1</category><icon src="http://sky.de/static/img/program_guide/14600235_s.jpg"/></programme>
<programme start="20240823133000 +0000" stop="20240823134500 +0000" channel="SkySportF1Germany.de"><title lang="de">F1: Top 10 Onboards: GP Belgien</title><category lang="de">Formel 1</category><icon src="http://sky.de/static/img/program_guide/14523033_s.jpg"/></programme>
<programme start="20240823134500 +0000" stop="20240823153000 +0000" channel="SkySportF1Germany.de"><title lang="de">Live F1: 2. Freies Training - GP Niederlande</title><category lang="de">Formel 1</category></programme>
<programme start="20240823153000 +0000" stop="20240823162000 +0000" channel="SkySportF1Germany.de"><title lang="de">Live F1 Academy: 2. Freies Training - GP Niederlande</title><category lang="de">Motorsport</category><icon src="http://sky.de/static/img/program_guide/14667616_s.jpg"/></programme>
<programme start="20240823162000 +0000" stop="20240823164500 +0000" channel="SkySportF1Germany.de"><title lang="de">F1: Inside Story: Magnificent Hamilton wins Silverstone classic</title><category lang="de">Formel 1</category><icon src="http://sky.de/static/img/program_guide/14667619_s.jpg"/></programme>
<programme start="20240823164500 +0000" stop="20240823170000 +0000" channel="SkySportF1Germany.de"><title lang="de">F1: Inside Story: Lando wins at last</title><category lang="de">Formel 1</category><icon src="http://sky.de/static/img/program_guide/14667620_s.jpg"/></programme>
<programme start="20240823170000 +0000" stop="20240823180000 +0000" channel="SkySportF1Germany.de"><title lang="de">IndyCar: Highlights: Bommarito Automotive Group 500</title><category lang="de">Motorsport</category></programme>
<programme start="20240823180000 +0000" stop="20240823193000 +0000" channel="SkySportF1Germany.de"><title lang="de">F1: 1. Freies Training - GP Niederlande</title><category lang="de">Formel 1</category></programme>
<programme start="20240823193000 +0000" stop="20240823210000 +0000" channel="SkySportF1Germany.de"><title lang="de">F1: 2. Freies Training - GP Niederlande</title><category lang="de">Formel 1</category></programme>
<programme start="20240823210000 +0000" stop="20240823220000 +0000" channel="SkySportF1Germany.de"><title lang="de">F1: Hardenacke trifft... (Gast: Ralf Schumacher)</title><category lang="de">Formel 1</category><icon src="http://sky.de/static/img/program_guide/14675205_s.jpg"/></programme>
<programme start="20240821053000 +0000" stop="20240821080000 +0000" channel="SkySportBundesligaUHD.de"><title lang="de">BL: Bayer Leverkusen - VfB Stuttgart, DFL Supercup 2024</title><category lang="de">Fußball</category></programme>
<programme start="20240821080000 +0000" stop="20240821100000 +0000" channel="SkySportBundesligaUHD.de"><title lang="de">2. BL: Hamburger SV - Hertha BSC, tipico Topspiel der Woche, 2. Spieltag</title><category lang="de">Fußball</category></programme>
<programme start="20240821100000 +0000" stop="20240821123000 +0000" channel="SkySportBundesligaUHD.de"><title lang="de">BL: Bayer Leverkusen - VfB Stuttgart, DFL Supercup 2024</title><category lang="de">Fußball</category></programme>
<programme start="20240821123000 +0000" stop="20240821143000 +0000" channel="SkySportBundesligaUHD.de"><title lang="de">BL: Bayer Leverkusen - FC Augsburg, 34. Spieltag</title><category lang="de">Fußball</category><icon src="http://sky.de/static/img/program_guide/14492872_s.jpg"/></programme>
<programme start="20240821143000 +0000" stop="20240821163000 +0000" channel="SkySportBundesligaUHD.de"><title lang="de">2. BL: FC Schalke 04 - Eintracht Braunschweig, tipico Topspiel der Woche, 1. Spieltag</title><category lang="de">Fußball</category><icon src="http://sky.de/static/img/program_guide/14601698_s.jpg"/></programme>
<programme start="20240821163000 +0000" stop="20240821183000 +0000" channel="SkySportBundesligaUHD.de"><title lang="de">2. BL: Hamburger SV - Hertha BSC, tipico Topspiel der Woche, 2. Spieltag</title><category lang="de">Fußball</category></programme>
<programme start="20240821183000 +0000" stop="20240821210000 +0000" channel="SkySportBundesligaUHD.de"><title lang="de">BL: Bayer Leverkusen - VfB Stuttgart, DFL Supercup 2024</title><category lang="de">Fußball</category></programme>
<programme start="20240821210000 +0000" stop="20240821230000 +0000" channel="SkySportBundesligaUHD.de"><title lang="de">2. BL: Hamburger SV - Hertha BSC, tipico Topspiel der Woche, 2. Spieltag</title><category lang="de">Fußball</category></programme>
<programme start="20240821230000 +0000" stop="20240822013000 +0000" channel="SkySportBundesligaUHD.de"><title lang="de">BL: Bayer Leverkusen - VfB Stuttgart, DFL Supercup 2024</title><category lang="de">Fußball</category></programme>
<programme start="20240822013000 +0000" stop="20240822033000 +0000" channel="SkySportBundesligaUHD.de"><title lang="de">2. BL: Hamburger SV - Hertha BSC, tipico Topspiel der Woche, 2. Spieltag</title><category lang="de">Fußball</category></programme>
<programme start="20240822033000 +0000" stop="20240822060000 +0000" channel="SkySportBundesligaUHD.de"><title lang="de">BL: Bayer Leverkusen - VfB Stuttgart, DFL Supercup 2024</title><category lang="de">Fußball</category></programme>
<programme start="20240822060000 +0000" stop="20240822061500 +0000" channel="SkySportBundesligaUHD.de"><title lang="de">Info: UHD</title></programme>
<programme start="20240823073000 +0000" stop="20240823093000 +0000" channel="SkySportBundesligaUHD.de"><title lang="de">BL: 1. FC Heidenheim - FC Bayern München, 28. Spieltag</title><category lang="de">Fußball</category></programme>
<programme start="20240823093000 +0000" stop="20240823113000 +0000" channel="SkySportBundesligaUHD.de"><title lang="de">BL: Borussia Dortmund - VfB Stuttgart, tipico Topspiel der Woche, 28. Spieltag</title><category lang="de">Fußball</category><icon src="http://sky.de/static/img/program_guide/14429604_s.jpg"/></programme>
<programme start="20240823113000 +0000" stop="20240823133000 +0000" channel="SkySportBundesligaUHD.de"><title lang="de">BL: FC Bayern München - 1. FC Köln, 29. Spieltag</title><category lang="de">Fußball</category></programme>
<programme start="20240823133000 +0000" stop="20240823153000 +0000" channel="SkySportBundesligaUHD.de"><title lang="de">BL: VfB Stuttgart - Eintracht Frankfurt, tipico Topspiel der Woche, 29. Spieltag</title><category lang="de">Fußball</category></programme>
<programme start="20240823153000 +0000" stop="20240823173000 +0000" channel="SkySportBundesligaUHD.de"><title lang="de">BL: 1. FC Köln - SV Darmstadt 98, 30.Spieltag</title><category lang="de">Fußball</category></programme>
<programme start="20240823173000 +0000" stop="20240823193000 +0000" channel="SkySportBundesligaUHD.de"><title lang="de">BL: 1. FC Union Berlin - FC Bayern München, tipico Topspiel der Woche, 30. Spieltag</title><category lang="de">Fußball</category></programme>
<programme start="20240823193000 +0000" stop="20240823213000 +0000" channel="SkySportBundesligaUHD.de"><title lang="de">BL: FC Bayern München - Eintracht Frankfurt, 31. Spieltag</title><category lang="de">Fußball</category></programme>
<programme start="20240823213000 +0000" stop="20240823233000 +0000" channel="SkySportBundesligaUHD.de"><title lang="de">BL: Bayer Leverkusen - VfB Stuttgart, tipico Topspiel der Woche, 31. Spieltag</title><category lang="de">Fußball</category></programme>
</tv>